<annotation>
	<folder>JPEGImage</folder>
	<filename>408082a2-ea4e-11e9-a49e-b025aa21b04b.jpg</filename>
	<path>F:\Yolov5\VOC2007\JPEGImage\408082a2-ea4e-11e9-a49e-b025aa21b04b.jpg</path>
	<source>
		<database>Unknown</database>
	</source>
	<size>
		<width>130</width>
		<height>155</height>
		<depth>3</depth>
	</size>
	<segmented>0</segmented>
	<object>
		<name>zhoujielun</name>
		<pose>Unspecified</pose>
		<truncated>0</truncated>
		<difficult>0</difficult>
		<bndbox>
			<xmin>28</xmin>
			<ymin>14</ymin>
			<xmax>120</xmax>
			<ymax>140</ymax>
		</bndbox>
	</object>
</annotation>
